compudoc/__init__.py
compudoc/__main__.py
compudoc/document.py
compudoc/examples.py
compudoc/execution_engines.py
compudoc/parsing.py
compudoc/template_engines.py
compudoc-0.11.2.dist-info/METADATA
compudoc-0.11.2.dist-info/WHEEL
compudoc-0.11.2.dist-info/entry_points.txt
compudoc-0.11.2.dist-info/RECORD
