Metadata-Version: 2.3
Name: compudoc
Version: 0.11.2
Summary: Add python calculations to your LaTeX and Markdown documents.
Author-email: CD Clark III <clifton.clark@gmail.com>
Classifier: Programming Language :: Python :: 3 :: Only
Classifier: Programming Language :: Python :: 3.9
Classifier: Programming Language :: Python :: 3.10
Classifier: Programming Language :: Python :: 3.11
Classifier: Programming Language :: Python :: 3.12
Classifier: Programming Language :: Python :: 3.13
Classifier: Programming Language :: Python :: 3.14
Requires-Python: >=3.9
Requires-Dist: art>=6.4
Requires-Dist: cyclopts>=3.1.2
Requires-Dist: fspathtree>=1
Requires-Dist: jinja2>=3.1.4
Requires-Dist: pint>=0.24.3
Requires-Dist: pyparsing[diagrams]>=3.1.4
